rapid/__init__.py
rapid/process.py
rapid/settings.py
jjromrapid-0.1.0.dist-info/LICENSE.txt
jjromrapid-0.1.0.dist-info/METADATA
jjromrapid-0.1.0.dist-info/WHEEL
jjromrapid-0.1.0.dist-info/top_level.txt
jjromrapid-0.1.0.dist-info/RECORD
